well_architected/__init__.py
well_architected/app.py
well_architected/well_architected_construct.py
well_architected/well_architected_stack.py
well_architected/regular_constructs/__init__.py
well_architected/regular_constructs/autoscaling_ecs.py
well_architected/regular_constructs/ecs_fargate_service.py
well_architected/regular_stacks/__init__.py
well_architected/regular_stacks/vpc_lamba.py
well_architected/regular_stacks/ecs/__init__.py
well_architected/regular_stacks/ecs/alb_autoscaling_ecs_service.py
well_architected/regular_stacks/ecs/autoscaling_ecs_cluster.py
well_architected/regular_stacks/ecs/autoscaling_ecs_service.py
well_architected/regular_stacks/ecs/autoscaling_ecs_service_with_placement.py
well_architected/regular_stacks/ecs/nlb_autoscaling_ecs_service.py
well_architected/regular_stacks/ecs/nlb_autoscaling_fargate_service.py
well_architected/regular_stacks/ecs/nlb_fargate_service.py
well_architected/regular_stacks/step_functions/__init__.py
well_architected/regular_stacks/step_functions/job_poller.py
well_architected/well_architected_constructs/__init__.py
well_architected/well_architected_constructs/api.py
well_architected/well_architected_constructs/api_lambda.py
well_architected/well_architected_constructs/api_lambda_dynamodb.py
well_architected/well_architected_constructs/dynamodb_table.py
well_architected/well_architected_constructs/http_api_step_functions.py
well_architected/well_architected_constructs/lambda_function.py
well_architected/well_architected_constructs/rest_api.py
well_architected/well_architected_constructs/rest_api_sns.py
well_architected/well_architected_constructs/sns_lambda.py
well_architected/well_architected_constructs/web_application_firewall.py
well_architected/well_architected_stacks/__init__.py
well_architected/well_architected_stacks/api_lambda_dynamodb.py
well_architected/well_architected_stacks/api_lambda_dynamodb_eventbridge_lambda.py
well_architected/well_architected_stacks/api_lambda_eventbridge_lambda.py
well_architected-1.0.3.dist-info/LICENSE
well_architected-1.0.3.dist-info/METADATA
well_architected-1.0.3.dist-info/WHEEL
well_architected-1.0.3.dist-info/top_level.txt
well_architected-1.0.3.dist-info/RECORD
