Metadata-Version: 2.1
Name: well-architected
Version: 1.0.3
Summary: CDK constructs and stacks based on the Well Architected Framework
Author-email: johnnyblase <johnnyblasin@gmail.com>
License: Copyright (c) 2022 JadeCobra LLC        
Project-URL: Homepage, https://github.com/jadecobra/well_architected
Project-URL: Bug Tracker, https://github.com/jadecobra/well_architected/issues
Classifier: Programming Language :: Python :: 3
Classifier: License :: OSI Approved :: MIT License
Classifier: Operating System :: OS Independent
Requires-Python: >=3.7
License-File: LICENSE
Requires-Dist: aws-cdk-lib
Requires-Dist: constructs
